{"code": "AUB101", "lang": "de", "description": "\nAuftragsbestand: Wertindex\n\nErl\u00e4uterung f\u00fcr folgende Statistik(en):\n44141 Statistik \u00fcber den Auftragsbestand im Bauhauptgew.\n\nBegriffsinhalt:\nDer Wertindex ist eine Messgr\u00f6\u00dfe f\u00fcr die nominale\nEntwicklung des Auftragsbestands im Bauhauptgewerbe.\nDer Auftragsbestand ist definiert als Summe der Werte aller\nim Berichtszeitraum akzeptierten noch nicht ausgef\u00fchrten\nBauauftr\u00e4ge.\n\n\n\u00a9 Statistisches Bundesamt, Wiesbaden 2017", "name": "Auftragsbestand: Wertindex", "type": "Merkmal"}