{"code": "BEVPR2", "lang": "en", "description": "\nVariants of the population projection\n\nExplanatory notes for the following statistics:\n12421 Population projections\n\nDefinition:\nAssumptions underlying the 13th coordinated population\nprojection variants (based on: 31 December 2013):\n- Variant 1 \"Continued trend based on lower immigration\":\nG1-L1-W1\n- Variant 2 \"Continued trend based on higher immigration\":\nG1-L1-W2\n\nG1: Birth rate 1.4 children per woman\nL1: Life expectancy at birth in 2060 84.8 years for boys\nand 88.8 years for girls\nW1: Long-term migration balance 100,000\nW2: Long-term migration balance 200,000\n\n\n\u00a9 Statistisches Bundesamt, Wiesbaden 2015", "name": "Variants of the population projection", "type": "variable"}