{"code": "EGS001", "lang": "en", "description": "\nRecipients of basic security benefits in old age and in\ncases of reduced earning capacity\n\nExplanatory notes for the following statistics:\n22151 Basic security in old age, reduced earning capacity\n\nDefinition:\nPeople who have reached the age limit described in Section\n41 (2) of the Social Code, Book XII, and who receive basic\nsecurity benefits in old age as well as people aged from 18\nto under the age limit who are permanently unfit for work\nand receive basic security benefits because of their reduced\nearning capacity.\n\n\n\u00a9 Statistisches Bundesamt, Wiesbaden 2016", "name": "Recipients of basic security benefits", "type": "variable"}