{"code": "KINHH1", "lang": "de", "description": "\nKinder unter 18 Jahren\n\nErl\u00e4uterung f\u00fcr folgende Statistik(en):\n12211 Mikrozensus\n\nBegriffsinhalt:\nKinder sind ledige Personen, die mit ihren Eltern oder einem\nElternteil, z.B. der geschiedenen Mutter, in einem Haushalt,\neiner Familie bzw. in einer nichtehelichen Lebens-\ngemeinschaft zusammen leben. Eine Altersbegrenzung f\u00fcr die\nZ\u00e4hlung als Kind besteht nicht. Als Kinder gelten auch\nledige Stief-, Adoptiv- oder Pflegekinder, sofern die zuvor\ngenannten Voraussetzungen vorliegen.\n\n\n\u00a9 Statistisches Bundesamt, Wiesbaden 2016", "name": "Kinder unter 18 Jahren", "type": "Merkmal"}