{"code": "PER100", "lang": "en", "description": "\nRegelleistungsberechtigte nach dem SGB II\n\n\nErl\u00e4uterung f\u00fcr folgende Statistik(en):\n22811 Sozialberichterstattung\n\nBegriffsinhalt:\nRegelleistungsberechtigte nach dem SGB II\n\nRegelleistungsberechtigte sind Personen mit Anspruch auf\nGesamtregelleistung (Arbeitslosengeld II oder Sozialgeld).\nDazu z\u00e4hlen Personen, die Anspruch auf folgende Leistungs-\narten haben:\n\n- Regelbedarf Arbeitslosengeld II oder Sozialgeld (\u00a7\u00a7 20, 23\nSGB II)\n\n- Mehrbedarfe (\u00a7 21 SGB II)\n\n- laufende und einmalige Leistungen f\u00fcr Unterkunft und Hei-\nzung einschlie\u00dflich Nachzahlung von Heiz- und Betriebs-\nkosten sowie Heizmittelbevorratung, Wohnbeschaffungs-\nkosten, Mietschulden und Instandhaltungs- und Reparatur-\nkosten bei selbst bewohntem Wohneigentum (\u00a7 22 SGB II) und\n\n- efristeter Zuschlag nach dem Bezug von Arbeitslosengeld\n(\u00a7 24 SGB II a.F., entfallen ab 1. Januar 2011).\n\nGesamtregelleistung (Arbeitslosengeld II und Sozialgeld) um-\nfasst den Regelbedarf zur Sicherung des Lebensunterhalts,\nLeistungen f\u00fcr Mehrbedarfe, Kosten der Unterkunft, sowie bis\nzum 31.12.2010 den befristeten Zuschlag nach Bezug von Ar-\nbeitslosengeld gem\u00e4\u00df \u00a7 24 SGB II (alte Fassung). Die Gesamt-\nregelleistung setzt sich aus Arbeitslosengeld II f\u00fcr er-\nwerbsf\u00e4hige Leistungsberechtigte und Sozialgeld f\u00fcr nicht\nerwerbsf\u00e4hige Leistungsberechtigte zusammen.", "name": null, "type": "Merkmal"}