{"code": "SITC1A", "lang": "en", "description": "\nStandard International Trade Classification (SITC),\nSITC (1-digit codes): Foreign trade\n\nExplanatory notes for the following statistics:\n51000 Foreign trade\n\nDefinition:\nThe Standard International Trade Classification (SITC) forms\nthe basis for classifying goods in foreign trade statistics.\nIt differs from the Harmonised System for describing and\ncoding goods and the Combined Nomenclature only in that it\nprovides a higher aggregation of commodity groups and a\nstructure that is clearly based on statistical requirements.\n\n\n\u00a9 Statistisches Bundesamt, Wiesbaden 2017", "name": "SITC (1-digit codes): Foreign trade", "type": "variable"}