{"code": "STAAG6", "lang": "de", "description": "\nStaatsangeh\u00f6rigkeit\n\nErl\u00e4uterung f\u00fcr folgende Statistik(en):\n12511 Einb\u00fcrgerungsstatistik\n12521 Ausl\u00e4nderstatistik\n\nBegriffsinhalt:\nDie Staatsangeh\u00f6rigkeit ist eine besondere Rechtsbeziehung,\ndie eine Person einem bestimmten Staat zuordnet.\nGegen\u00fcber allen anderen Staaten ist diese Person Ausl\u00e4nder.\nPersonen, die keine Staatsangeh\u00f6rigkeit besitzen, sind\nstaatenlos. Mit der Staatsangeh\u00f6rigkeit sind Rechte\n(diplomatischer Schutz im Ausland, Wahlrecht) und Pflichten\n(Wehrpflicht) verbunden.\n\nVor 2004 war die Staatsangeh\u00f6rigkeit von \"Serbien und\nMontenegro\" mit der der \"Bundesrepublik Jugoslawien\"\nidentisch; ab August 2006 werden auch die\nStaatsangeh\u00f6rigkeiten der beiden Nachfolgestaaten \"Serbien\"\nund \"Montenegro\" nachgewiesen. Ab 01.05.2008 wird zus\u00e4tzlich\nKosovo getrennt nachgewiesen.\n\nLDR-GASTARB, Gastarbeiterl\u00e4nder:\nBosnien und Herzegowina, Griechenland, Italien, Kosovo,\nKroatien, Marokko, Mazedonien, Montenegro, Portugal, Serbien\n(mit und ohne Kosovo), Slowenien, Spanien, T\u00fcrkei, Tunesien,\neinschlie\u00dflich Personen mit der Staatsangeh\u00f6rigkeit des\nehemaligen Serbien und Montenegro und des ehemaligen\n(Gesamt-)Jugoslawiens ohne n\u00e4here Angabe. Korea, Republik\n(S\u00fcdkorea) wurde nicht mit aufgenommen.\n\nLDR-YU, Gebiet des ehemaligen Jugoslawien:\nBosnien und Herzegowina, Kosovo, Kroatien, Mazedonien,\nMontenegro, Serbien (mit und ohne Kosovo), Slowenien,\neinschlie\u00dflich Personen mit der Staatsangeh\u00f6rigkeit des\nehemaligen Serbien und Montenegro und des ehemaligen\n(Gesamt-)Jugoslawiens ohne n\u00e4here Angabe.\n\nLDR-SM, Gebiet des ehemaligen Serbien und Montenegro:\nKosovo, Montenegro, Serbien (mit und ohne Kosovo),\nehemaliges Serbien und Montenegro.\n\nLDR-SU, Gebiet der ehemaligen Sowjetunion:\nArmenien, Aserbaidschan, Estland, Georgien, Kasachstan,\nKirgisistan, Lettland, Litauen, Republik Moldau, Russische\nF\u00f6deration, Tadschikistan, Turkmenistan, Ukraine,\nUsbekistan, Wei\u00dfrussland (Belarus) einschlie\u00dflich Personen\nmit der Staatsangeh\u00f6rigkeit der ehemaligen Sowjetunion ohne\nn\u00e4here Angabe.\n\nLDR-CZ, Gebiet der ehemaligen Tschechoslowakei:\nTschechische Republik, Slowakei, einschlie\u00dflich Personen mit\nder Staatsangeh\u00f6rigkeit der ehemaligen Tschechoslowakei ohne\nn\u00e4here Angabe.\n\nLDR-GB, Gebiet des Vereinigten K\u00f6nigreiches einschlie\u00dflich\nder britischen \u00dcberseegebiete:\nVereinigtes K\u00f6nigreich einschlie\u00dflich Personen mit der\nStaatsangeh\u00f6rigkeit der britischen \u00dcberseegebiete auf\nau\u00dfereurop\u00e4ischen Kontinenten. Ausl\u00e4nder der britischen\n\u00dcberseegebiete sind keine EU-B\u00fcrger.\n\n\n\u00a9 Statistisches Bundesamt, Wiesbaden 2016", "name": "Staatsangeh\u00f6rigkeit", "type": "Merkmal"}