{"code": "VBR028", "lang": "de", "description": "\nEnergieverbrauch (Anteil am Bruttoproduktionswert)\n\nErl\u00e4uterung f\u00fcr folgende Statistik(en):\n42251 Kostenstrukturerhebung im Verarb. Gewerbe, Bergbau\n\nBegriffsinhalt:\nEnergieverbrauch ist der Gesamtverbrauch an Brenn- und\nTreibstoffen, Elektrizit\u00e4t, Gas, W\u00e4rme u. dgl..\nWasser, als Bestandteil der Roh-, Hilfs- und Betriebsstoffe,\nist nicht im Energieverbrauch enthalten.\n\n\u00a9 Statistisches Bundesamt, Wiesbaden 2004", "name": "Energieverbrauch (Anteil am BPW)", "type": "Merkmal"}