{"code": "VDT001", "lang": "en", "description": "\nSuspects having attained the age of criminal responsibility\n\nExplanatory notes for the following statistics:\n24911 Police crime statistics\n\nDefinition:\nA suspect is anyone who, according to police investigation,\nis sufficiently suspected to have committed a criminal\noffence.\nThe age of criminal responsibility means that the relevant\nperson was 14 years old or over when the offence was\ncommitted (Section 19 of the Criminal Code).\n\n\n\u00a9 Statistisches Bundesamt, Wiesbaden 2017", "name": "Suspects hav. attained the age of crim. responsib.", "type": "variable"}